setup.py
bubbles/__init__.py
bubbles/common.py
bubbles/core.py
bubbles/datautil.py
bubbles/doc.py
bubbles/errors.py
bubbles/extensions.py
bubbles/iterator.py
bubbles/metadata.py
bubbles/objects.py
bubbles/pipeline.py
bubbles/stores.py
bubbles/urlresource.py
bubbles.egg-info/PKG-INFO
bubbles.egg-info/SOURCES.txt
bubbles.egg-info/dependency_links.txt
bubbles.egg-info/top_level.txt
bubbles/backends/__init__.py
bubbles/backends/sql/__init__.py
bubbles/backends/sql/objects.py
bubbles/backends/sql/ops.py
bubbles/backends/sql/utils.py
bubbles/backends/text/__init__.py
bubbles/backends/text/objects.py