Metadata-Version: 1.1
Name: bubbles
Version: 0.1
Summary: Virtual Data Object framework for data processing (ETL) and quality monitoring
Home-page: http://bubbles.databrewery.org
Author: Stefan Urbanek
Author-email: stefan.urbanek@gmail.com
License: MIT
Keywords: data analysis quality datamining
Platform: UNKNOWN
Classifier: Development Status :: 4 - Beta
Classifier: Intended Audience :: Developers
Classifier: Intended Audience :: Science/Research
Classifier: License :: OSI Approved :: MIT License
Classifier: Programming Language :: Python
Classifier: Topic :: Database
Classifier: Topic :: Scientific/Engineering
Classifier: Topic :: Utilities
